[{"equipmentName":"深海之王-支配：青","magicalDefense":1939,"strength":42,"intelligence":42,"specialEffect":"进入地下城时，减少50点力量。\n全属性强化+9\n全部职业50级技能等级+1（特性技能除外）\n智力+3%","equipmentQuality":"史诗","applicableLevel":50,"equipmentType":"戒指"},{"equipmentName":"斗者的天袭指环","magicalDefense":1801,"strength":39,"intelligence":39,"specialEffect":"连击数20时，在10秒内移动/攻击/释放速度+10%(10秒冷却)","equipmentQuality":"史诗","applicableLevel":50,"equipmentType":"戒指"},{"equipmentName":"深海之王-支配：赤","magicalDefense":1939,"strength":42,"intelligence":42,"specialEffect":"进入地下城时，减少50点智力。\n全属性强化+9\n全部职业50级技能等级+1（特性技能除外）\n力量+3%","equipmentQuality":"史诗","applicableLevel":50,"equipmentType":"戒指"},{"equipmentName":"魂·疯狂伊凡的炸药包","magicalDefense":1801,"strength":39,"intelligence":39,"specialEffect":"生命值在10%以下时，被攻击时可以引起强力爆炸，对地图内所有怪物造成20万点伤害，同时角色减少10%的生命值。\n\n火属性强化+9","equipmentQuality":"史诗","applicableLevel":50,"equipmentType":"戒指"},{"equipmentName":"魂·疯狂伊凡的避火装置","magicalDefense":1801,"strength":39,"intelligence":39,"specialEffect":"火属性强化+8","equipmentQuality":"史诗","applicableLevel":50,"equipmentType":"戒指"},{"equipmentName":"蓝色真谛求知之戒","magicalDefense":1801,"strength":39,"intelligence":39,"accuracy":80,"specialEffect":"攻击时，有5%几率恢复10%MP(冷却5秒)\n\n魔法防御力+3%","equipmentQuality":"史诗","applicableLevel":50,"equipmentType":"戒指"},{"equipmentName":"史苏克的一滴眼泪","magicalDefense":1801,"strength":39,"intelligence":39,"specialEffect":"攻击时，有3%几率增加10点冰属性强化，持续10秒\n\n冰属性抗性+7","equipmentQuality":"史诗","applicableLevel":50,"equipmentType":"戒指"},{"equipmentName":"时空主宰者戒指","magicalDefense":1801,"strength":39,"intelligence":39,"specialEffect":"施放技能时，有5%几率使当前冷却30秒内的技能中冷却时间最短的技能重置(冷却时间30秒)","equipmentQuality":"史诗","applicableLevel":50,"equipmentType":"戒指"},{"equipmentName":"潜行团员之刃戒指","magicalDefense":1801,"strength":39,"intelligence":39,"specialEffect":"对HP50%以上的敌人暴击攻击时伤害增加5%\n对HP50%以下的敌人暴击攻击时伤害增加10%","equipmentQuality":"史诗","applicableLevel":50,"equipmentType":"戒指"},{"equipmentName":"刺击理性戒指","magicalDefense":1801,"strength":39,"intelligence":39,"spirit":110,"specialEffect":"攻击时，有3%几率触发以下效果之一(冷却时间60秒)\n- 当前冷却60秒内的所有技能重置\n- 当前冷却60秒内的所有技能的冷却时间调整为2倍","equipmentQuality":"史诗","applicableLevel":50,"equipmentType":"戒指"},{"equipmentName":"踌躇者的罗盘戒指","magicalDefense":1801,"strength":39,"intelligence":39,"accuracy":80,"specialEffect":"全部属性强化+10","equipmentQuality":"史诗","applicableLevel":50,"equipmentType":"戒指"},{"equipmentName":"重量分流之戒","physicalAttack":17,"magicalAttack":17,"magicalDefense":1801,"strength":39,"vitality":39,"attackSpeed":0.04,"specialEffect":"攻击时，有2%几率消耗1块铁片在60秒内物理、魔法攻击力+15(60秒冷却)","equipmentQuality":"史诗","applicableLevel":50,"equipmentType":"戒指"},{"equipmentName":"窒息的悲鸣之戒","magicalDefense":1607,"strength":35,"intelligence":35,"attackSpeed":0.025,"moveSpeed":0.025,"specialEffect":"全属性强化+4","equipmentQuality":"神器","applicableLevel":50,"equipmentType":"戒指"},{"equipmentName":"骸麒的戒指","magicalDefense":1330,"strength":29,"intelligence":29,"specialEffect":"破招物理攻击时，可以提高50%的伤害","equipmentQuality":"神器","applicableLevel":40,"equipmentType":"戒指"}]